.dada-version
MANIFEST.in
README.md
requirements.txt
setup.cfg
setup.py
dada_settings/__init__.py
dada_settings/cons.py
dada_settings/core.py
dada_settings/dev.py
dada_settings/docker.py
dada_settings/prod.py
dada_settings/test.py
dada_settings/utils.py
dada_settings.egg-info/PKG-INFO
dada_settings.egg-info/SOURCES.txt
dada_settings.egg-info/dependency_links.txt
dada_settings.egg-info/requires.txt
dada_settings.egg-info/top_level.txt
dada_settings/constants/__init__.py
dada_settings/constants/desktop_defaults.py
dada_settings/constants/field_defaults.py
dada_settings/constants/file_audio_defaults.py
dada_settings/constants/file_bundle_defaults.py
dada_settings/constants/file_code_defaults.py
dada_settings/constants/file_data_defaults.py
dada_settings/constants/file_defaults.py
dada_settings/constants/file_doc_defaults.py
dada_settings/constants/file_image_defaults.py
dada_settings/constants/file_model_defaults.py
dada_settings/constants/file_store_defaults.py
dada_settings/constants/file_video_defaults.py
dada_settings/constants/tag_defaults.py
dada_settings/constants/theme_defaults.py
dada_settings/gen/__init__.py
dada_settings/gen/desktop_defaults.py
dada_settings/gen/field_defaults.py
dada_settings/gen/folder_defaults.py
dada_settings/models/__init__.py
dada_settings/models/core.py
dada_settings/models/desktop_defaults.py
dada_settings/models/file_audio_defaults.py
dada_settings/models/file_bundle_defaults.py
dada_settings/models/file_code_defaults.py
dada_settings/models/file_data_defaults.py
dada_settings/models/file_defaults.py
dada_settings/models/file_doc_defaults.py
dada_settings/models/file_image_defaults.py
dada_settings/models/file_model_defaults.py
dada_settings/models/file_video_defaults.py
dada_settings/models/folder_defaults.py
dada_settings/models/tag_defaults.py
dada_settings/models/user_defaults.py